zubr/__init__.py
zubr/classification.py
zubr/fetcher.py
zubr/metrics.py
zubr/parallel.py
zubr/utilities.py
zubr/ab/__init__.py
zubr/ab/designing.py
zubr/ab/stratification.py
zubr/generators/__init__.py
zubr/generators/point_data.py
zubr/knn/__init__.py
zubr/knn/test_knn.py
zubr/plot/__init__.py
zubr/plot/classification.py
zubr/plot/plot_data.py
zubr/plot/plot_metrics.py
zubr/plot/plot_points.py
zubr/prepare/__init__.py
zubr/prepare/metrics.py
zubr/prepare/norm.py
zubr/svm/__init__.py
zubr/svm/test_svm.py
zubr/trees/__init__.py
zubr/trees/test_classification.py
zubr/trees/test_regression.py
zubr-0.0.2.dist-info/LICENSE
zubr-0.0.2.dist-info/METADATA
zubr-0.0.2.dist-info/WHEEL
zubr-0.0.2.dist-info/top_level.txt
zubr-0.0.2.dist-info/RECORD
